src/dailytreasuryrates-cache.csv
dailytreasuryrates.py
dailytreasuryrates-0.4.5.dist-info/LICENSE
dailytreasuryrates-0.4.5.dist-info/METADATA
dailytreasuryrates-0.4.5.dist-info/WHEEL
dailytreasuryrates-0.4.5.dist-info/entry_points.txt
dailytreasuryrates-0.4.5.dist-info/RECORD
