Metadata-Version: 2.1
Name: dailytreasuryrates
Version: 0.4.5
Summary: Daily Treasury Rates Downloader
License: MIT
Author: Thijs van den Berg
Author-email: thijs@sitmo.com
Requires-Python: >=3.8,<4.0
Classifier: License :: OSI Approved :: MIT License
Classifier: Programming Language :: Python :: 3
Classifier: Programming Language :: Python :: 3.8
Classifier: Programming Language :: Python :: 3.9
Classifier: Programming Language :: Python :: 3.10
Classifier: Programming Language :: Python :: 3.11
Classifier: Programming Language :: Python :: 3.12
Requires-Dist: argparse (>=1.1.0,<2.0.0)
Requires-Dist: pandas (>=2.0,<3.0)
